toastuieditor/__init__.py
toastuieditor/admin.py
toastuieditor/apps.py
toastuieditor/fields.py
toastuieditor/models.py
toastuieditor/plugins.py
toastuieditor/tests.py
toastuieditor/urls.py
toastuieditor/views.py
toastuieditor/widgets.py
toastuieditor/migrations/0001_initial.py
toastuieditor/migrations/__init__.py
toastuieditor/static/toastuieditor/toastui-editor-all.js
toastuieditor/static/toastuieditor/toastui-editor-all.min.js
toastuieditor/static/toastuieditor/toastui-editor-only.css
toastuieditor/static/toastuieditor/toastui-editor-only.min.css
toastuieditor/static/toastuieditor/toastui-editor-viewer.css
toastuieditor/static/toastuieditor/toastui-editor-viewer.js
toastuieditor/static/toastuieditor/toastui-editor-viewer.min.css
toastuieditor/static/toastuieditor/toastui-editor-viewer.min.js
toastuieditor/static/toastuieditor/toastui-editor.css
toastuieditor/static/toastuieditor/toastui-editor.js
toastuieditor/static/toastuieditor/toastui-editor.min.css
toastuieditor/static/toastuieditor/toastui-editor.min.js
toastuieditor/static/toastuieditor/i18n/ar.js
toastuieditor/static/toastuieditor/i18n/ar.min.js
toastuieditor/static/toastuieditor/i18n/cs-cz.js
toastuieditor/static/toastuieditor/i18n/cs-cz.min.js
toastuieditor/static/toastuieditor/i18n/de-de.js
toastuieditor/static/toastuieditor/i18n/de-de.min.js
toastuieditor/static/toastuieditor/i18n/es-es.js
toastuieditor/static/toastuieditor/i18n/es-es.min.js
toastuieditor/static/toastuieditor/i18n/fi-fi.js
toastuieditor/static/toastuieditor/i18n/fi-fi.min.js
toastuieditor/static/toastuieditor/i18n/fr-fr.js
toastuieditor/static/toastuieditor/i18n/fr-fr.min.js
toastuieditor/static/toastuieditor/i18n/gl-es.js
toastuieditor/static/toastuieditor/i18n/gl-es.min.js
toastuieditor/static/toastuieditor/i18n/hr-hr.js
toastuieditor/static/toastuieditor/i18n/hr-hr.min.js
toastuieditor/static/toastuieditor/i18n/it-it.js
toastuieditor/static/toastuieditor/i18n/it-it.min.js
toastuieditor/static/toastuieditor/i18n/ja-jp.js
django_toastuieditor-0.0.1.dist-info/LICENSE
django_toastuieditor-0.0.1.dist-info/METADATA
django_toastuieditor-0.0.1.dist-info/WHEEL
django_toastuieditor-0.0.1.dist-info/top_level.txt
django_toastuieditor-0.0.1.dist-info/RECORD
