Metadata-Version: 2.1
Name: django-toastuieditor
Version: 0.0.1
Summary: 一个toastuieditor的django包
Author-email: xingfuggz <1158920674@qq.com>
Project-URL: Homepage, http://www.bayke.shop
Project-URL: Bug Tracker, http://www.bayke.shop
Classifier: Programming Language :: Python :: 3
Classifier: License :: OSI Approved :: MIT License
Classifier: Operating System :: OS Independent
Requires-Python: >=3.7
License-File: LICENSE
